custom_user_tests/__init__.py
custom_user_tests/apps.py
custom_user_tests/forms.py
custom_user_tests/models.py
custom_user_tests/settings.py
custom_user_tests/migrations/0001_initial.py
custom_user_tests/migrations/__init__.py
custom_user_tests/tests/__init__.py
custom_user_tests/tests/test_custom_user_model.py
lazysignup/__init__.py
lazysignup/admin.py
lazysignup/apps.py
lazysignup/backends.py
lazysignup/constants.py
lazysignup/decorators.py
lazysignup/exceptions.py
lazysignup/forms.py
lazysignup/models.py
lazysignup/signals.py
lazysignup/urls.py
lazysignup/utils.py
lazysignup/version.py
lazysignup/views.py
lazysignup/management/__init__.py
lazysignup/management/commands/__init__.py
lazysignup/management/commands/remove_expired_users.py
lazysignup/migrations/0001_initial.py
lazysignup/migrations/0002_auto_20150430_1100.py
lazysignup/migrations/__init__.py
lazysignup/templates/lazysignup/convert.html
lazysignup/templates/lazysignup/done.html
lazysignup/templatetags/__init__.py
lazysignup/templatetags/lazysignup_tags.py
lazysignup/tests/__init__.py
lazysignup/tests/forms.py
lazysignup/tests/settings.py
lazysignup/tests/test_backend.py
lazysignup/tests/test_manager.py
lazysignup/tests/test_models.py
lazysignup/tests/test_template_tags.py
lazysignup/tests/tests.py
lazysignup/tests/urls.py
lazysignup/tests/views.py
django_lazysignup-2.0.0.dist-info/LICENSE.txt
django_lazysignup-2.0.0.dist-info/METADATA
django_lazysignup-2.0.0.dist-info/WHEEL
django_lazysignup-2.0.0.dist-info/top_level.txt
django_lazysignup-2.0.0.dist-info/RECORD
