Metadata-Version: 2.1
Name: django-lazysignup
Version: 2.0.0
Summary: Lazy signup for Django
Home-page: http://github.com/danfairs/django-lazysignup
Author: Dan Fairs
Author-email: dan.fairs@gmail.com
License: BSD
Keywords: django lazy signup app user
Platform: UNKNOWN
Classifier: Programming Language :: Python
Classifier: Programming Language :: Python :: 2.7
Classifier: Programming Language :: Python :: 3.4
Classifier: Topic :: Software Development :: Libraries :: Python Modules
Classifier: Framework :: Django
Classifier: Framework :: Django :: 1.10
Classifier: Development Status :: 4 - Beta
Classifier: License :: OSI Approved :: BSD License
Provides-Extra: docs
Provides-Extra: test
Provides-Extra: all
Provides-Extra: packaging
